System_Information/__init__.py
System_Information/__main__.py
System_Information-1.0.dist-info/LICENSE
System_Information-1.0.dist-info/METADATA
System_Information-1.0.dist-info/WHEEL
System_Information-1.0.dist-info/entry_points.txt
System_Information-1.0.dist-info/top_level.txt
System_Information-1.0.dist-info/RECORD
