Metadata-Version: 2.1
Name: System-Information
Version: 1.0
Summary: It finds basic information about the system.
Home-page: UNKNOWN
Author: Udit Vashisht
Author-email: admin@saralgyaan.com
License: MIT
Platform: UNKNOWN
Classifier: License :: OSI Approved :: MIT License
Classifier: Programming Language :: Python :: 3.8
Classifier: Programming Language :: Python :: 3.9
License-File: LICENSE
Requires-Dist: wmi
Requires-Dist: platform
